{
  "https://github.com/modelcontextprotocol/servers/tree/main/src/github": {
    "name": "github",
    "description": "GitHub server",
    "installationMethods": {
      "nodeModule": {
        "npmPackage": "@modelcontextprotocol/server-github",
        "envVars": {
          "GITHUB_PERSONAL_ACCESS_TOKEN": "Your personal access token to Github"
        }
      },
      "docker": {
        "image": "modelcontextprotocol/server-github",
        "envVars": {
          "GITHUB_PERSONAL_ACCESS": "Your personal access token to Github"
        }
      }
    }
  }
}
